methodkit/__init__.py
methodkit/py.typed
methodkit/picking/__init__.py
methodkit/picking/roulette_wheel.py
methodkit/picking/numpy/__init__.py
methodkit/picking/numpy/roulette_wheel.py
methodkit/utils/__init__.py
methodkit/utils/conditional.py
methodkit-0.2.0.dist-info/METADATA
methodkit-0.2.0.dist-info/WHEEL
methodkit-0.2.0.dist-info/licenses/LICENSE
methodkit-0.2.0.dist-info/RECORD
